wbkit/__init__.py
wbkit/basic.py
wbkit/cglimits.py
wbkit/plfunc.py
wbkit/py.typed
wbkit-0.0.6.dist-info/LICENSE
wbkit-0.0.6.dist-info/METADATA
wbkit-0.0.6.dist-info/WHEEL
wbkit-0.0.6.dist-info/top_level.txt
wbkit-0.0.6.dist-info/RECORD
